pysigfox/__init__.py
pysigfox/constants.py
pysigfox/exceptions.py
pysigfox/sigfox.py
pysigfox/utils.py
pysigfox_client-0.1.4.dist-info/LICENSE
pysigfox_client-0.1.4.dist-info/METADATA
pysigfox_client-0.1.4.dist-info/WHEEL
pysigfox_client-0.1.4.dist-info/top_level.txt
pysigfox_client-0.1.4.dist-info/RECORD
