Metadata-Version: 2.1
Name: pysigfox-client
Version: 0.1.4
Summary: Unofficial client for the Sigfox V2 API
Home-page: https://github.com/optimdata/pysigfox
Author: Othman Moumni Abdou
Author-email: othman.moumniabdou@inuse.eu
License: MIT license
Keywords: sigfox
Platform: UNKNOWN
Classifier: Development Status :: 3 - Alpha
Classifier: Intended Audience :: Developers
Classifier: License :: OSI Approved :: MIT License
Classifier: Natural Language :: English
Classifier: Programming Language :: Python :: 3
Classifier: Programming Language :: Python :: 3.6
Classifier: Programming Language :: Python :: 3.7
Requires-Dist: requests
